vuecore/README.md
vuecore/__init__.py
vuecore/color_list.py
vuecore/constants.py
vuecore/decomposition.py
vuecore/dendrogram.py
vuecore/linkers.py
vuecore/metrics.py
vuecore/translate.py
vuecore/utils_old.py
vuecore/viz.py
vuecore/wgcna.py
vuecore/engines/__init__.py
vuecore/engines/registry.py
vuecore/engines/plotly/__init__.py
vuecore/engines/plotly/bar.py
vuecore/engines/plotly/box.py
vuecore/engines/plotly/histogram.py
vuecore/engines/plotly/line.py
vuecore/engines/plotly/plot_builder.py
vuecore/engines/plotly/saver.py
vuecore/engines/plotly/scatter.py
vuecore/engines/plotly/theming.py
vuecore/engines/plotly/violin.py
vuecore/plots/__init__.py
vuecore/plots/plot_factory.py
vuecore/plots/basic/__init__.py
vuecore/plots/basic/bar.py
vuecore/plots/basic/box.py
vuecore/plots/basic/histogram.py
vuecore/plots/basic/line.py
vuecore/plots/basic/scatter.py
vuecore/plots/basic/violin.py
vuecore/schemas/__init__.py
vuecore/schemas/plotly_base.py
vuecore/schemas/basic/bar.py
vuecore/schemas/basic/box.py
vuecore/schemas/basic/histogram.py
vuecore/schemas/basic/line.py
vuecore/schemas/basic/scatter.py
vuecore/schemas/basic/violin.py
vuecore/utils/__init__.py
vuecore/utils/docs_utils.py
vuecore/utils/statistics.py
vuecore-0.1.1.dist-info/licenses/LICENSE.md
vuecore-0.1.1.dist-info/METADATA
vuecore-0.1.1.dist-info/WHEEL
vuecore-0.1.1.dist-info/top_level.txt
vuecore-0.1.1.dist-info/RECORD
